mtel_client/__init__.py
mtel_client/client.py
mtel_client/exc.py
mtel_client/models.py
mtel_client-0.0.1.dev3.dist-info/METADATA
mtel_client-0.0.1.dev3.dist-info/WHEEL
mtel_client-0.0.1.dev3.dist-info/licenses/LICENSE
mtel_client-0.0.1.dev3.dist-info/RECORD
